simple_diarizer/__init__.py
simple_diarizer/cluster.py
simple_diarizer/diarizer.py
simple_diarizer/utils.py
simple_diarizer-0.0.13.dist-info/LICENSE
simple_diarizer-0.0.13.dist-info/METADATA
simple_diarizer-0.0.13.dist-info/WHEEL
simple_diarizer-0.0.13.dist-info/top_level.txt
simple_diarizer-0.0.13.dist-info/RECORD
