Metadata-Version: 2.1
Name: simple-diarizer
Version: 0.0.13
Summary: Simplified diarization pipeline using some pretrained models - audio file to diarized segments in a few lines of code
Author: Chau Luu
Author-email: cvqluu@gmail.com
Classifier: Programming Language :: Python :: 3
Classifier: Operating System :: OS Independent
Requires-Python: >=3.7
License-File: LICENSE
Requires-Dist: ipython (>=7.9.0)
Requires-Dist: matplotlib (>=3.5.1)
Requires-Dist: pandas (>=1.3.5)
Requires-Dist: scikit-learn (>=1.0.2)
Requires-Dist: speechbrain (>=0.5.11)
Requires-Dist: torchaudio (>=0.10.1)
